sharkpoint/__init__.py
sharkpoint/sharepoint.py
sharkpoint/sharepoint_file.py
sharkpoint/sharepoint_site.py
sharkpoint-3.0.dist-info/LICENSE
sharkpoint-3.0.dist-info/WHEEL
sharkpoint-3.0.dist-info/METADATA
sharkpoint-3.0.dist-info/RECORD
