Metadata-Version: 2.1
Name: sharkpoint
Version: 3.0
Summary: A small Pythonic library for interacting with SharePoint document libraries
Author: TheOtherOne
Requires-Python: >=3.7
Classifier: Programming Language :: Python :: 3
Classifier: License :: OSI Approved :: MIT License
Classifier: Operating System :: OS Independent
Classifier: Topic :: Office/Business
Classifier: Topic :: Internet :: WWW/HTTP
Requires-Dist: requests >=2.6
Requires-Dist: azure-identity
Project-URL: Bug Tracker, https://github.com/ThatsItForTheOtherOne/sharkpoint/issues
Project-URL: Homepage, https://github.com/ThatsItForTheOtherOne/sharkpoint
